MANIFEST.in
README.md
setup.py
actions/__init__.py
actions/api.py
actions/base.py
actions/fields.py
actions/helpers.py
actions/legacy.py
actions/mixins.py
actions/models.py
actions/util.py
actions/actions/__init__.py
actions/actions/action_registry.py
actions/actions/archive_actions/__init__.py
actions/actions/archive_actions/form.py
actions/actions/archive_actions/tests/__init__.py
actions/actions/archive_actions/tests/test_api.py
actions/actions/archive_actions/tests/test_form.py
actions/forms/__init__.py
actions/forms/mixins.py
actions/management/__init__.py
actions/management/commands/__init__.py
actions/management/commands/create_action.py
actions/management/commands/helpers.py
actions/management/commands/start_actions.py
actions/migrations/0001_initial.py
actions/migrations/__init__.py
actions/templates/djactions/README.md
actions/templates/djactions/action_registry.py
actions/templates/djactions/create_action_confirmation.txt
actions/templates/djactions/create_action_success.txt
actions/templates/djactions/definition.yaml
actions/templates/djactions/form.py
actions/templates/djactions/instructions.txt
actions/templates/djactions/test_api.py
actions/templates/djactions/test_form.py
actions/tests/__init__.py
actions/tests/test_actions.py
actions/tests/testutils.py
dj_actions.egg-info/PKG-INFO
dj_actions.egg-info/SOURCES.txt
dj_actions.egg-info/dependency_links.txt
dj_actions.egg-info/requires.txt
dj_actions.egg-info/top_level.txt
example_app/actions/__init__.py
example_app/actions/todo/__init__.py
example_app/actions/todo/action_registry.py
example_app/actions/todo/bulk_mark_done/__init__.py
example_app/actions/todo/bulk_mark_done/form.py
example_app/actions/todo/bulk_mark_done/tests/__init__.py
example_app/actions/todo/bulk_mark_done/tests/test_api.py
example_app/actions/todo/bulk_mark_done/tests/test_form.py
example_app/actions/todo/mark_done/__init__.py
example_app/actions/todo/mark_done/form.py
example_app/actions/todo/mark_done/tests/__init__.py
example_app/actions/todo/mark_done/tests/test_api.py
example_app/actions/todo/mark_done/tests/test_form.py
example_app/migrations/0001_initial.py
