Metadata-Version: 2.1
Name: dj-actions
Version: 0.0.7
Summary: UNKNOWN
Home-page: https://gitlab.com/schoolorchestration/libs/dj-actions
Author: Christo Crampton
Author-email: info@38.co.za
License: UNKNOWN
Platform: UNKNOWN
Classifier: Programming Language :: Python :: 3
Classifier: Operating System :: OS Independent
